HISTORY.txt
LICENSE.txt
README.txt
setup.py
collective/__init__.py
collective.saoraclefixes.egg-info/PKG-INFO
collective.saoraclefixes.egg-info/SOURCES.txt
collective.saoraclefixes.egg-info/dependency_links.txt
collective.saoraclefixes.egg-info/entry_points.txt
collective.saoraclefixes.egg-info/not-zip-safe
collective.saoraclefixes.egg-info/requires.txt
collective.saoraclefixes.egg-info/top_level.txt
collective/saoraclefixes/__init__.py