Metadata-Version: 1.0
Name: collective.saoraclefixes
Version: 1.2
Summary: Fixes for the SQLAlchemy 0.4 and 0.5 Oracle driver
Home-page: http://svn.plone.org/svn/collective/collective.saoraclefixes
Author: Jarn AS
Author-email: info@jarn.com
License: MIT
Keywords: sqlalchemy oracle reservedwords quoting bindparam
Platform: UNKNOWN
